<?xml version="1.0"?>
<dolfin xmlns:dolfin="http://fenicsproject.org">
  <function_data size="784">
    <dof index="0" value="-8.7545147088900307e-07" cell_index="611" cell_dof_index="0" />
    <dof index="1" value="2.6373982084472112e-07" cell_index="611" cell_dof_index="3" />
    <dof index="2" value="-8.7615652410141983e-07" cell_index="610" cell_dof_index="2" />
    <dof index="3" value="1.3609091794472614e-07" cell_index="610" cell_dof_index="5" />
    <dof index="4" value="-7.4578813023924684e-07" cell_index="611" cell_dof_index="2" />
    <dof index="5" value="2.6303476763230462e-07" cell_index="611" cell_dof_index="5" />
    <dof index="6" value="-8.7980579870515047e-07" cell_index="559" cell_dof_index="0" />
    <dof index="7" value="1.1036358511124265e-08" cell_index="559" cell_dof_index="3" />
    <dof index="8" value="-7.3411288790716227e-07" cell_index="558" cell_dof_index="1" />
    <dof index="9" value="1.2397167267434116e-07" cell_index="558" cell_dof_index="4" />
    <dof index="10" value="-6.1340322950189581e-07" cell_index="347" cell_dof_index="0" />
    <dof index="11" value="2.5933926704675853e-07" cell_index="347" cell_dof_index="3" />
    <dof index="12" value="-7.4655035882124122e-07" cell_index="391" cell_dof_index="2" />
    <dof index="13" value="-3.5643634991541785e-08" cell_index="391" cell_dof_index="5" />
    <dof index="14" value="-6.0081263310852727e-07" cell_index="174" cell_dof_index="0" />
    <dof index="15" value="-2.3996516884917602e-10" cell_index="174" cell_dof_index="3" />
    <dof index="16" value="-5.9343601966287328e-07" cell_index="347" cell_dof_index="1" />
    <dof index="17" value="1.270229161354654e-07" cell_index="347" cell_dof_index="4" />
    <dof index="18" value="-4.7996805718344798e-07" cell_index="347" cell_dof_index="2" />
    <dof index="19" value="2.494677132388286e-07" cell_index="347" cell_dof_index="5" />
    <dof index="20" value="-8.8891581394036216e-07" cell_index="385" cell_dof_index="2" />
    <dof index="21" value="-1.143865117928431e-07" cell_index="385" cell_dof_index="5" />
    <dof index="22" value="-7.0454546110249029e-07" cell_index="174" cell_dof_index="1" />
    <dof index="23" value="-1.6515843901019672e-07" cell_index="174" cell_dof_index="4" />
    <dof index="24" value="-4.6071850122063633e-07" cell_index="174" cell_dof_index="2" />
    <dof index="25" value="-1.3217706899933565e-07" cell_index="174" cell_dof_index="5" />
    <dof index="26" value="-3.540826241847409e-07" cell_index="286" cell_dof_index="2" />
    <dof index="27" value="-4.0090437923896668e-08" cell_index="286" cell_dof_index="5" />
    <dof index="28" value="-4.1612042879934601e-07" cell_index="260" cell_dof_index="2" />
    <dof index="29" value="7.3460776709668324e-08" cell_index="260" cell_dof_index="5" />
    <dof index="30" value="-3.5153354251477909e-07" cell_index="260" cell_dof_index="0" />
    <dof index="31" value="2.3407339158118694e-07" cell_index="260" cell_dof_index="3" />
    <dof index="32" value="-9.0236931738456366e-07" cell_index="385" cell_dof_index="0" />
    <dof index="33" value="-2.4481427028812806e-07" cell_index="385" cell_dof_index="3" />
    <dof index="34" value="-5.6792240611979879e-07" cell_index="73" cell_dof_index="0" />
    <dof index="35" value="-3.075196699377649e-07" cell_index="73" cell_dof_index="3" />
    <dof index="36" value="-7.6477307491271052e-07" cell_index="73" cell_dof_index="2" />
    <dof index="37" value="-3.1029220341453073e-07" cell_index="73" cell_dof_index="5" />
    <dof index="38" value="-9.2180124729523914e-07" cell_index="400" cell_dof_index="2" />
    <dof index="39" value="-3.8481150894760422e-07" cell_index="400" cell_dof_index="5" />
    <dof index="40" value="-3.4234430463511867e-07" cell_index="175" cell_dof_index="1" />
    <dof index="41" value="-3.2808969234706155e-07" cell_index="175" cell_dof_index="4" />
    <dof index="42" value="-2.6000311536898796e-07" cell_index="285" cell_dof_index="0" />
    <dof index="43" value="-1.2756358425381834e-07" cell_index="285" cell_dof_index="3" />
    <dof index="44" value="-2.3734935065807426e-07" cell_index="176" cell_dof_index="2" />
    <dof index="45" value="-2.9852834884926292e-08" cell_index="176" cell_dof_index="5" />
    <dof index="46" value="-2.2477978503254541e-07" cell_index="176" cell_dof_index="1" />
    <dof index="47" value="6.6361161262872846e-08" cell_index="176" cell_dof_index="4" />
    <dof index="48" value="-2.3388776328336132e-07" cell_index="626" cell_dof_index="2" />
    <dof index="49" value="2.1148448281616589e-07" cell_index="626" cell_dof_index="5" />
    <dof index="50" value="-7.1975507830231556e-07" cell_index="73" cell_dof_index="1" />
    <dof index="51" value="-4.6647688065030339e-07" cell_index="73" cell_dof_index="4" />
    <dof index="52" value="-5.3205096509059818e-07" cell_index="214" cell_dof_index="2" />
    <dof index="53" value="-5.1163438509800045e-07" cell_index="214" cell_dof_index="5" />
    <dof index="54" value="-3.6703865842722705e-07" cell_index="276" cell_dof_index="0" />
    <dof index="55" value="-5.8774481864987857e-07" cell_index="276" cell_dof_index="3" />
    <dof index="56" value="-2.5672106128766776e-07" cell_index="276" cell_dof_index="2" />
    <dof index="57" value="-4.4807460780034179e-07" cell_index="276" cell_dof_index="5" />
    <dof index="58" value="-2.1630395045099574e-07" cell_index="295" cell_dof_index="2" />
    <dof index="59" value="-2.6061371587728285e-07" cell_index="295" cell_dof_index="5" />
    <dof index="60" value="-1.1375965065917164e-07" cell_index="147" cell_dof_index="1" />
    <dof index="61" value="-1.7500499917199782e-07" cell_index="147" cell_dof_index="4" />
    <dof index="62" value="-8.0721536528625901e-08" cell_index="147" cell_dof_index="0" />
    <dof index="63" value="-4.3353713706769331e-08" cell_index="147" cell_dof_index="3" />
    <dof index="64" value="-9.3100655124898516e-08" cell_index="199" cell_dof_index="1" />
    <dof index="65" value="6.4747886800796676e-08" cell_index="199" cell_dof_index="4" />
    <dof index="66" value="-1.2375840438426441e-07" cell_index="252" cell_dof_index="0" />
    <dof index="67" value="1.836105707440809e-07" cell_index="252" cell_dof_index="3" />
    <dof index="68" value="-9.404409860576147e-07" cell_index="400" cell_dof_index="0" />
    <dof index="69" value="-5.3805669188828049e-07" cell_index="400" cell_dof_index="3" />
    <dof index="70" value="-6.5515102771753337e-07" cell_index="148" cell_dof_index="0" />
    <dof index="71" value="-6.9362272482528418e-07" cell_index="148" cell_dof_index="3" />
    <dof index="72" value="-4.8300443092709688e-07" cell_index="148" cell_dof_index="1" />
    <dof index="73" value="-7.4978354581881249e-07" cell_index="148" cell_dof_index="4" />
    <dof index="74" value="-2.7389868599385868e-07" cell_index="165" cell_dof_index="2" />
    <dof index="75" value="-6.9848674489183331e-07" cell_index="165" cell_dof_index="5" />
    <dof index="76" value="-1.540309999733342e-07" cell_index="207" cell_dof_index="1" />
    <dof index="77" value="-6.223051633197786e-07" cell_index="207" cell_dof_index="4" />
    <dof index="78" value="-1.3246785753564437e-07" cell_index="185" cell_dof_index="0" />
    <dof index="79" value="-3.4286701825507379e-07" cell_index="185" cell_dof_index="3" />
    <dof index="80" value="-1.0085231989126929e-08" cell_index="135" cell_dof_index="1" />
    <dof index="81" value="-2.1714155595906822e-07" cell_index="135" cell_dof_index="4" />
    <dof index="82" value="-1.6018223207138999e-08" cell_index="135" cell_dof_index="2" />
    <dof index="83" value="-1.1246349818353925e-07" cell_index="135" cell_dof_index="5" />
    <dof index="84" value="5.0733617550904912e-08" cell_index="4" cell_dof_index="1" />
    <dof index="85" value="-6.5137909743476907e-09" cell_index="4" cell_dof_index="4" />
    <dof index="86" value="-1.2995933857492641e-08" cell_index="199" cell_dof_index="2" />
    <dof index="87" value="3.1465539315815639e-08" cell_index="199" cell_dof_index="5" />
    <dof index="88" value="-3.2679186462875061e-08" cell_index="253" cell_dof_index="1" />
    <dof index="89" value="1.4862634425174394e-07" cell_index="253" cell_dof_index="4" />
    <dof index="90" value="-8.0172950054341405e-07" cell_index="247" cell_dof_index="2" />
    <dof index="91" value="-6.1776471776200784e-07" cell_index="247" cell_dof_index="5" />
    <dof index="92" value="-9.6075686194221709e-07" cell_index="247" cell_dof_index="1" />
    <dof index="93" value="-7.0746139573122802e-07" cell_index="247" cell_dof_index="4" />
    <dof index="94" value="-6.0402060991608452e-07" cell_index="148" cell_dof_index="2" />
    <dof index="95" value="-8.7408004509336278e-07" cell_index="148" cell_dof_index="5" />
    <dof index="96" value="-7.6876044181102454e-07" cell_index="229" cell_dof_index="1" />
    <dof index="97" value="-8.6177695906107659e-07" cell_index="229" cell_dof_index="4" />
    <dof index="98" value="-9.7292256709763013e-07" cell_index="401" cell_dof_index="0" />
    <dof index="99" value="-8.9122253643142305e-07" cell_index="401" cell_dof_index="3" />
    <dof index="100" value="-3.4330458974141046e-07" cell_index="165" cell_dof_index="0" />
    <dof index="101" value="-8.7543320326360086e-07" cell_index="165" cell_dof_index="3" />
    <dof index="102" value="-5.2704598315886329e-07" cell_index="210" cell_dof_index="0" />
    <dof index="103" value="-1.0678958154776501e-06" cell_index="210" cell_dof_index="3" />
    <dof index="104" value="-1.6070929184627224e-07" cell_index="207" cell_dof_index="0" />
    <dof index="105" value="-9.8408207309892848e-07" cell_index="207" cell_dof_index="3" />
    <dof index="106" value="-2.9457827609629533e-08" cell_index="186" cell_dof_index="2" />
    <dof index="107" value="-7.7451108401046756e-07" cell_index="186" cell_dof_index="5" />
    <dof index="108" value="-1.6799237191022682e-08" cell_index="209" cell_dof_index="2" />
    <dof index="109" value="-4.8505408445074171e-07" cell_index="209" cell_dof_index="5" />
    <dof index="110" value="1.1207308215405835e-08" cell_index="185" cell_dof_index="2" />
    <dof index="111" value="-3.2755595631306311e-07" cell_index="185" cell_dof_index="5" />
    <dof index="112" value="8.7086574250648452e-08" cell_index="113" cell_dof_index="2" />
    <dof index="113" value="-2.2746002519567942e-07" cell_index="113" cell_dof_index="5" />
    <dof index="114" value="7.1987174270482016e-08" cell_index="50" cell_dof_index="2" />
    <dof index="115" value="-1.4123216789956458e-07" cell_index="50" cell_dof_index="5" />
    <dof index="116" value="5.8034674699399907e-08" cell_index="4" cell_dof_index="2" />
    <dof index="117" value="-7.2306850622178296e-08" cell_index="4" cell_dof_index="5" />
    <dof index="118" value="8.990701508907646e-08" cell_index="4" cell_dof_index="0" />
    <dof index="119" value="-3.6266055455317786e-08" cell_index="4" cell_dof_index="3" />
    <dof index="120" value="7.8374692494894782e-08" cell_index="1" cell_dof_index="0" />
    <dof index="121" value="1.2904543830885441e-08" cell_index="1" cell_dof_index="3" />
    <dof index="122" value="4.154743885542518e-08" cell_index="134" cell_dof_index="2" />
    <dof index="123" value="5.0985613373404876e-08" cell_index="134" cell_dof_index="5" />
    <dof index="124" value="3.2411541436398258e-08" cell_index="111" cell_dof_index="1" />
    <dof index="125" value="1.1030852262523133e-07" cell_index="111" cell_dof_index="4" />
    <dof index="126" value="-7.6679936298148908e-07" cell_index="215" cell_dof_index="1" />
    <dof index="127" value="-1.0909358136192262e-06" cell_index="215" cell_dof_index="4" />
    <dof index="128" value="-5.8836548069427763e-07" cell_index="215" cell_dof_index="2" />
    <dof index="129" value="-1.2610511038852827e-06" cell_index="215" cell_dof_index="5" />
    <dof index="130" value="-4.0479567316516084e-07" cell_index="192" cell_dof_index="2" />
    <dof index="131" value="-1.3998560883085803e-06" cell_index="192" cell_dof_index="5" />
    <dof index="132" value="-3.1289260216102081e-07" cell_index="192" cell_dof_index="1" />
    <dof index="133" value="-1.2114397273994088e-06" cell_index="192" cell_dof_index="4" />
    <dof index="134" value="-1.0446459098701608e-07" cell_index="208" cell_dof_index="1" />
    <dof index="135" value="-1.3933746487844233e-06" cell_index="208" cell_dof_index="4" />
    <dof index="136" value="-1.1045430080325314e-08" cell_index="208" cell_dof_index="2" />
    <dof index="137" value="-1.1328408818563661e-06" cell_index="208" cell_dof_index="5" />
    <dof index="138" value="6.1738975630564343e-08" cell_index="409" cell_dof_index="2" />
    <dof index="139" value="-9.3010679969244148e-07" cell_index="409" cell_dof_index="5" />
    <dof index="140" value="1.3301909567264872e-07" cell_index="57" cell_dof_index="1" />
    <dof index="141" value="-7.0879701785139567e-07" cell_index="57" cell_dof_index="4" />
    <dof index="142" value="1.1579888102281836e-07" cell_index="25" cell_dof_index="2" />
    <dof index="143" value="-4.9944877691810785e-07" cell_index="25" cell_dof_index="5" />
    <dof index="144" value="1.0180968900936022e-07" cell_index="25" cell_dof_index="1" />
    <dof index="145" value="-3.4001660166521484e-07" cell_index="25" cell_dof_index="4" />
    <dof index="146" value="1.4853051189830633e-07" cell_index="13" cell_dof_index="0" />
    <dof index="147" value="-2.3669284788551666e-07" cell_index="13" cell_dof_index="3" />
    <dof index="148" value="1.2393935514149503e-07" cell_index="14" cell_dof_index="2" />
    <dof index="149" value="-1.5546627442435822e-07" cell_index="14" cell_dof_index="5" />
    <dof index="150" value="1.0423365208579709e-07" cell_index="7" cell_dof_index="0" />
    <dof index="151" value="-8.9656242065387023e-08" cell_index="7" cell_dof_index="3" />
    <dof index="152" value="1.037765341844327e-07" cell_index="7" cell_dof_index="2" />
    <dof index="153" value="-3.4844991185204871e-08" cell_index="7" cell_dof_index="5" />
    <dof index="154" value="9.1980828961098076e-08" cell_index="1" cell_dof_index="1" />
    <dof index="155" value="6.6494842798350607e-09" cell_index="1" cell_dof_index="4" />
    <dof index="156" value="8.2533037513637064e-08" cell_index="1" cell_dof_index="2" />
    <dof index="157" value="4.4927190856153894e-08" cell_index="1" cell_dof_index="5" />
    <dof index="158" value="6.9524731664456768e-08" cell_index="3" cell_dof_index="2" />
    <dof index="159" value="5.7629994713110128e-08" cell_index="3" cell_dof_index="5" />
    <dof index="160" value="7.4751795548468952e-08" cell_index="5" cell_dof_index="2" />
    <dof index="161" value="6.9563041580569712e-08" cell_index="5" cell_dof_index="5" />
    <dof index="162" value="-9.7540207067232086e-07" cell_index="608" cell_dof_index="2" />
    <dof index="163" value="-1.0927096094150582e-06" cell_index="608" cell_dof_index="5" />
    <dof index="164" value="-9.6549198959143203e-07" cell_index="232" cell_dof_index="0" />
    <dof index="165" value="-1.3042440190608899e-06" cell_index="232" cell_dof_index="3" />
    <dof index="166" value="-7.3534691027147733e-07" cell_index="232" cell_dof_index="2" />
    <dof index="167" value="-1.3424506869351745e-06" cell_index="232" cell_dof_index="5" />
    <dof index="168" value="-5.5224392238215497e-07" cell_index="233" cell_dof_index="0" />
    <dof index="169" value="-1.486745475762643e-06" cell_index="233" cell_dof_index="3" />
    <dof index="170" value="-4.0463943651713222e-07" cell_index="377" cell_dof_index="2" />
    <dof index="171" value="-1.7045367514619116e-06" cell_index="377" cell_dof_index="5" />
    <dof index="172" value="-2.7742202636359847e-07" cell_index="192" cell_dof_index="0" />
    <dof index="173" value="-1.5896965126281288e-06" cell_index="192" cell_dof_index="3" />
    <dof index="174" value="-1.0935988159142228e-07" cell_index="291" cell_dof_index="2" />
    <dof index="175" value="-1.6543286640201687e-06" cell_index="291" cell_dof_index="5" />
    <dof index="176" value="2.2962657267595673e-08" cell_index="169" cell_dof_index="2" />
    <dof index="177" value="-1.6846824269180985e-06" cell_index="169" cell_dof_index="5" />
    <dof index="178" value="1.2091141857286071e-07" cell_index="201" cell_dof_index="0" />
    <dof index="179" value="-1.3918538593545398e-06" cell_index="201" cell_dof_index="3" />
    <dof index="180" value="2.4769722442301547e-07" cell_index="149" cell_dof_index="2" />
    <dof index="181" value="-1.0890998536599393e-06" cell_index="149" cell_dof_index="5" />
    <dof index="182" value="2.5800403995394661e-07" cell_index="17" cell_dof_index="2" />
    <dof index="183" value="-6.585727322367759e-07" cell_index="17" cell_dof_index="5" />
    <dof index="184" value="2.0673913759139764e-07" cell_index="18" cell_dof_index="0" />
    <dof index="185" value="-5.4272036606460509e-07" cell_index="18" cell_dof_index="3" />
    <dof index="186" value="1.7572277488898722e-07" cell_index="20" cell_dof_index="2" />
    <dof index="187" value="-3.5716341579633268e-07" cell_index="20" cell_dof_index="5" />
    <dof index="188" value="1.7431102687503633e-07" cell_index="13" cell_dof_index="1" />
    <dof index="189" value="-2.0615808075995527e-07" cell_index="13" cell_dof_index="4" />
    <dof index="190" value="1.4315187292808206e-07" cell_index="13" cell_dof_index="2" />
    <dof index="191" value="-1.3707141012216542e-07" cell_index="13" cell_dof_index="5" />
    <dof index="192" value="1.1990498325474556e-07" cell_index="7" cell_dof_index="1" />
    <dof index="193" value="-7.8399754634496534e-08" cell_index="7" cell_dof_index="4" />
    <dof index="194" value="9.5468259634679886e-08" cell_index="105" cell_dof_index="2" />
    <dof index="195" value="-3.6144544212187971e-08" cell_index="105" cell_dof_index="5" />
    <dof index="196" value="9.7080608080105125e-08" cell_index="82" cell_dof_index="2" />
    <dof index="197" value="-1.3917905211382313e-08" cell_index="82" cell_dof_index="5" />
    <dof index="198" value="9.3181772401223321e-08" cell_index="82" cell_dof_index="1" />
    <dof index="199" value="1.2062712918173307e-08" cell_index="82" cell_dof_index="4" />
    <dof index="200" value="9.2272444990903363e-08" cell_index="5" cell_dof_index="1" />
    <dof index="201" value="4.7967763395343228e-08" cell_index="5" cell_dof_index="4" />
    <dof index="202" value="-9.38731281730168e-07" cell_index="489" cell_dof_index="2" />
    <dof index="203" value="-1.5268761876749813e-06" cell_index="489" cell_dof_index="5" />
    <dof index="204" value="-6.472707459979721e-07" cell_index="440" cell_dof_index="1" />
    <dof index="205" value="-1.7136005271376931e-06" cell_index="440" cell_dof_index="4" />
    <dof index="206" value="-4.5205953990078588e-07" cell_index="230" cell_dof_index="0" />
    <dof index="207" value="-1.9379799126910128e-06" cell_index="230" cell_dof_index="3" />
    <dof index="208" value="-2.7082849039224568e-07" cell_index="213" cell_dof_index="2" />
    <dof index="209" value="-1.9189610700217626e-06" cell_index="213" cell_dof_index="5" />
    <dof index="210" value="-1.1289502503293642e-07" cell_index="168" cell_dof_index="1" />
    <dof index="211" value="-1.9101827968107641e-06" cell_index="168" cell_dof_index="4" />
    <dof index="212" value="8.4165244205046041e-08" cell_index="169" cell_dof_index="0" />
    <dof index="213" value="-2.0184461078288218e-06" cell_index="169" cell_dof_index="3" />
    <dof index="214" value="1.8536785678166369e-07" cell_index="266" cell_dof_index="2" />
    <dof index="215" value="-1.8957894974617874e-06" cell_index="266" cell_dof_index="5" />
    <dof index="216" value="1.6507220761625553e-07" cell_index="367" cell_dof_index="1" />
    <dof index="217" value="-1.6625931845027897e-06" cell_index="367" cell_dof_index="4" />
    <dof index="218" value="3.3600506092239239e-07" cell_index="201" cell_dof_index="2" />
    <dof index="219" value="-1.4373100970351835e-06" cell_index="201" cell_dof_index="5" />
    <dof index="220" value="5.7120733507452827e-07" cell_index="149" cell_dof_index="1" />
    <dof index="221" value="-1.0885998361387907e-06" cell_index="149" cell_dof_index="4" />
    <dof index="222" value="4.2132941151450037e-07" cell_index="17" cell_dof_index="1" />
    <dof index="223" value="-6.3981732724481768e-07" cell_index="17" cell_dof_index="4" />
    <dof index="224" value="2.5734473165431602e-07" cell_index="12" cell_dof_index="0" />
    <dof index="225" value="-4.9918511966442444e-07" cell_index="12" cell_dof_index="3" />
    <dof index="226" value="2.1174484511192523e-07" cell_index="12" cell_dof_index="1" />
    <dof index="227" value="-3.1622826898362573e-07" cell_index="12" cell_dof_index="4" />
    <dof index="228" value="2.0633009492434076e-07" cell_index="8" cell_dof_index="2" />
    <dof index="229" value="-1.8049638292233162e-07" cell_index="8" cell_dof_index="5" />
    <dof index="230" value="1.3913743610825219e-07" cell_index="0" cell_dof_index="2" />
    <dof index="231" value="-9.7364715915450959e-08" cell_index="0" cell_dof_index="5" />
    <dof index="232" value="0" cell_index="0" cell_dof_index="0" />
    <dof index="233" value="0" cell_index="0" cell_dof_index="3" />
    <dof index="234" value="0" cell_index="105" cell_dof_index="1" />
    <dof index="235" value="0" cell_index="105" cell_dof_index="4" />
    <dof index="236" value="6.356855397530203e-08" cell_index="107" cell_dof_index="2" />
    <dof index="237" value="-1.1258453935803371e-08" cell_index="107" cell_dof_index="5" />
    <dof index="238" value="6.8623782302700839e-08" cell_index="82" cell_dof_index="0" />
    <dof index="239" value="-9.5128398343811061e-09" cell_index="82" cell_dof_index="3" />
    <dof index="240" value="1.2746973600128115e-07" cell_index="309" cell_dof_index="2" />
    <dof index="241" value="-7.4720621691734432e-08" cell_index="309" cell_dof_index="5" />
    <dof index="242" value="-8.9416166650030596e-07" cell_index="451" cell_dof_index="0" />
    <dof index="243" value="-1.7540271902221833e-06" cell_index="451" cell_dof_index="3" />
    <dof index="244" value="-6.1775969640482516e-07" cell_index="206" cell_dof_index="2" />
    <dof index="245" value="-1.970310948246752e-06" cell_index="206" cell_dof_index="5" />
    <dof index="246" value="-4.1086851115364407e-07" cell_index="230" cell_dof_index="1" />
    <dof index="247" value="-2.3179004384058829e-06" cell_index="230" cell_dof_index="4" />
    <dof index="248" value="-2.9833893595833118e-07" cell_index="188" cell_dof_index="2" />
    <dof index="249" value="-2.2352486469862859e-06" cell_index="188" cell_dof_index="5" />
    <dof index="250" value="-1.6871226509317023e-07" cell_index="168" cell_dof_index="0" />
    <dof index="251" value="-2.2405932621116611e-06" cell_index="168" cell_dof_index="3" />
    <dof index="252" value="-2.9010553666059776e-08" cell_index="168" cell_dof_index="2" />
    <dof index="253" value="-2.155939813657865e-06" cell_index="168" cell_dof_index="5" />
    <dof index="254" value="1.4357496087058941e-07" cell_index="290" cell_dof_index="2" />
    <dof index="255" value="-2.2280278400637929e-06" cell_index="290" cell_dof_index="5" />
    <dof index="256" value="3.224940487946979e-07" cell_index="267" cell_dof_index="2" />
    <dof index="257" value="-2.1160777655999921e-06" cell_index="267" cell_dof_index="5" />
    <dof index="258" value="3.1733780747405003e-07" cell_index="331" cell_dof_index="0" />
    <dof index="259" value="-1.7925631655056832e-06" cell_index="331" cell_dof_index="3" />
    <dof index="260" value="4.6148965344274078e-07" cell_index="331" cell_dof_index="2" />
    <dof index="261" value="-1.6448376736821092e-06" cell_index="331" cell_dof_index="5" />
    <dof index="262" value="6.2708557038098267e-07" cell_index="319" cell_dof_index="0" />
    <dof index="263" value="-1.4948637582733387e-06" cell_index="319" cell_dof_index="3" />
    <dof index="264" value="3.0561733436728632e-07" cell_index="12" cell_dof_index="2" />
    <dof index="265" value="-3.3082668247047353e-07" cell_index="12" cell_dof_index="5" />
    <dof index="266" value="1.5882343864887181e-07" cell_index="311" cell_dof_index="0" />
    <dof index="267" value="-1.4783846515504721e-07" cell_index="311" cell_dof_index="3" />
    <dof index="268" value="0" cell_index="0" cell_dof_index="1" />
    <dof index="269" value="0" cell_index="0" cell_dof_index="4" />
    <dof index="270" value="0" cell_index="582" cell_dof_index="0" />
    <dof index="271" value="0" cell_index="582" cell_dof_index="3" />
    <dof index="272" value="-8.2801363880107842e-07" cell_index="206" cell_dof_index="1" />
    <dof index="273" value="-1.9850180995128456e-06" cell_index="206" cell_dof_index="4" />
    <dof index="274" value="-7.3356793128640861e-07" cell_index="206" cell_dof_index="0" />
    <dof index="275" value="-2.2267317243001953e-06" cell_index="206" cell_dof_index="3" />
    <dof index="276" value="-6.1628127800415415e-07" cell_index="297" cell_dof_index="2" />
    <dof index="277" value="-2.4660043406625329e-06" cell_index="297" cell_dof_index="5" />
    <dof index="278" value="-3.360751678738738e-07" cell_index="6" cell_dof_index="2" />
    <dof index="279" value="-2.7062489344079995e-06" cell_index="6" cell_dof_index="5" />
    <dof index="280" value="-2.4929771442927567e-07" cell_index="28" cell_dof_index="1" />
    <dof index="281" value="-2.6744985886121765e-06" cell_index="28" cell_dof_index="4" />
    <dof index="282" value="-2.0031538463394944e-07" cell_index="188" cell_dof_index="1" />
    <dof index="283" value="-2.4835616259093672e-06" cell_index="188" cell_dof_index="4" />
    <dof index="284" value="-6.1227166230852573e-08" cell_index="156" cell_dof_index="1" />
    <dof index="285" value="-2.4357624094114496e-06" cell_index="156" cell_dof_index="4" />
    <dof index="286" value="4.8135537938077524e-08" cell_index="282" cell_dof_index="0" />
    <dof index="287" value="-2.3609208822087206e-06" cell_index="282" cell_dof_index="3" />
    <dof index="288" value="2.168015893303843e-07" cell_index="289" cell_dof_index="0" />
    <dof index="289" value="-2.3761257017593214e-06" cell_index="289" cell_dof_index="3" />
    <dof index="290" value="3.7285697242977027e-07" cell_index="335" cell_dof_index="2" />
    <dof index="291" value="-2.3233099174515276e-06" cell_index="335" cell_dof_index="5" />
    <dof index="292" value="5.5781042017448506e-07" cell_index="267" cell_dof_index="0" />
    <dof index="293" value="-2.1730055096008142e-06" cell_index="267" cell_dof_index="3" />
    <dof index="294" value="6.1071185131686988e-07" cell_index="267" cell_dof_index="1" />
    <dof index="295" value="-1.8560534153723904e-06" cell_index="267" cell_dof_index="4" />
    <dof index="296" value="0" cell_index="312" cell_dof_index="1" />
    <dof index="297" value="0" cell_index="312" cell_dof_index="4" />
    <dof index="298" value="-4.4290714203293576e-07" cell_index="6" cell_dof_index="1" />
    <dof index="299" value="-2.7120428846948086e-06" cell_index="6" cell_dof_index="4" />
    <dof index="300" value="-2.9929091215146993e-07" cell_index="2" cell_dof_index="2" />
    <dof index="301" value="-2.8254988715484561e-06" cell_index="2" cell_dof_index="5" />
    <dof index="302" value="-2.6881007579196897e-07" cell_index="2" cell_dof_index="1" />
    <dof index="303" value="-2.7966125506026153e-06" cell_index="2" cell_dof_index="4" />
    <dof index="304" value="-1.8401531310817208e-07" cell_index="34" cell_dof_index="2" />
    <dof index="305" value="-2.8324432484024621e-06" cell_index="34" cell_dof_index="5" />
    <dof index="306" value="-1.6037769243488829e-07" cell_index="166" cell_dof_index="2" />
    <dof index="307" value="-2.681353389491131e-06" cell_index="166" cell_dof_index="5" />
    <dof index="308" value="-9.2545629010321908e-08" cell_index="156" cell_dof_index="0" />
    <dof index="309" value="-2.6444824035851355e-06" cell_index="156" cell_dof_index="3" />
    <dof index="310" value="-3.4192602426994576e-08" cell_index="156" cell_dof_index="2" />
    <dof index="311" value="-2.5998050795389005e-06" cell_index="156" cell_dof_index="5" />
    <dof index="312" value="4.7206589205550179e-08" cell_index="196" cell_dof_index="0" />
    <dof index="313" value="-2.6334365264217091e-06" cell_index="196" cell_dof_index="3" />
    <dof index="314" value="1.3755507610048299e-07" cell_index="289" cell_dof_index="2" />
    <dof index="315" value="-2.547665341593049e-06" cell_index="289" cell_dof_index="5" />
    <dof index="316" value="2.1250355713294327e-07" cell_index="245" cell_dof_index="1" />
    <dof index="317" value="-2.6007615360426193e-06" cell_index="245" cell_dof_index="4" />
    <dof index="318" value="4.535879750872303e-07" cell_index="353" cell_dof_index="1" />
    <dof index="319" value="-2.4400025665529864e-06" cell_index="353" cell_dof_index="4" />
    <dof index="320" value="-2.9178306469976264e-07" cell_index="23" cell_dof_index="2" />
    <dof index="321" value="-2.9406216042578181e-06" cell_index="23" cell_dof_index="5" />
    <dof index="322" value="-2.0185742064636784e-07" cell_index="2" cell_dof_index="0" />
    <dof index="323" value="-2.9627077186496098e-06" cell_index="2" cell_dof_index="3" />
    <dof index="324" value="-1.8477237961187268e-07" cell_index="24" cell_dof_index="1" />
    <dof index="325" value="-2.9328497764110179e-06" cell_index="24" cell_dof_index="4" />
    <dof index="326" value="-1.2215114726412922e-07" cell_index="32" cell_dof_index="1" />
    <dof index="327" value="-2.9390286988262398e-06" cell_index="32" cell_dof_index="4" />
    <dof index="328" value="-9.2958171489609134e-08" cell_index="92" cell_dof_index="1" />
    <dof index="329" value="-2.8301660757303155e-06" cell_index="92" cell_dof_index="4" />
    <dof index="330" value="-2.0501845483141251e-08" cell_index="92" cell_dof_index="2" />
    <dof index="331" value="-2.7347337259345167e-06" cell_index="92" cell_dof_index="5" />
    <dof index="332" value="3.0175084325886395e-08" cell_index="299" cell_dof_index="0" />
    <dof index="333" value="-2.8015110430312781e-06" cell_index="299" cell_dof_index="3" />
    <dof index="334" value="7.9877304631513552e-08" cell_index="236" cell_dof_index="2" />
    <dof index="335" value="-2.7129203854215565e-06" cell_index="236" cell_dof_index="5" />
    <dof index="336" value="1.0641386029318813e-07" cell_index="236" cell_dof_index="0" />
    <dof index="337" value="-2.7556037052153201e-06" cell_index="236" cell_dof_index="3" />
    <dof index="338" value="1.9670254207757537e-07" cell_index="301" cell_dof_index="2" />
    <dof index="339" value="-2.7027607554258965e-06" cell_index="301" cell_dof_index="5" />
    <dof index="340" value="3.2912393771719144e-07" cell_index="336" cell_dof_index="0" />
    <dof index="341" value="-2.6396155298240068e-06" cell_index="336" cell_dof_index="3" />
    <dof index="342" value="-1.6698526454723552e-07" cell_index="37" cell_dof_index="1" />
    <dof index="343" value="-3.08629791422597e-06" cell_index="37" cell_dof_index="4" />
    <dof index="344" value="-1.9472862060153211e-07" cell_index="37" cell_dof_index="2" />
    <dof index="345" value="-3.0438926452694934e-06" cell_index="37" cell_dof_index="5" />
    <dof index="346" value="-1.1555231261025759e-07" cell_index="24" cell_dof_index="2" />
    <dof index="347" value="-3.0424398793514732e-06" cell_index="24" cell_dof_index="5" />
    <dof index="348" value="-1.0720164455606947e-07" cell_index="32" cell_dof_index="0" />
    <dof index="349" value="-3.0135436812515383e-06" cell_index="32" cell_dof_index="3" />
    <dof index="350" value="-5.8320706561938018e-08" cell_index="32" cell_dof_index="2" />
    <dof index="351" value="-2.9992638907943228e-06" cell_index="32" cell_dof_index="5" />
    <dof index="352" value="-6.6109345805762571e-08" cell_index="325" cell_dof_index="2" />
    <dof index="353" value="-2.9288913143910125e-06" cell_index="325" cell_dof_index="5" />
    <dof index="354" value="-2.8653158846162008e-08" cell_index="92" cell_dof_index="0" />
    <dof index="355" value="-2.8623364369621389e-06" cell_index="92" cell_dof_index="3" />
    <dof index="356" value="1.3182648760123924e-09" cell_index="369" cell_dof_index="2" />
    <dof index="357" value="-2.860175556096873e-06" cell_index="369" cell_dof_index="5" />
    <dof index="358" value="7.3613623138003474e-09" cell_index="246" cell_dof_index="0" />
    <dof index="359" value="-2.86481477930858e-06" cell_index="246" cell_dof_index="3" />
    <dof index="360" value="4.3958807675738326e-08" cell_index="236" cell_dof_index="1" />
    <dof index="361" value="-2.8235283737011392e-06" cell_index="236" cell_dof_index="4" />
    <dof index="362" value="6.4200282161554114e-08" cell_index="483" cell_dof_index="2" />
    <dof index="363" value="-2.8092739776702812e-06" cell_index="483" cell_dof_index="5" />
    <dof index="364" value="6.8807579802900252e-08" cell_index="345" cell_dof_index="2" />
    <dof index="365" value="-2.8149721994867926e-06" cell_index="345" cell_dof_index="5" />
    <dof index="366" value="1.7477004488192689e-07" cell_index="345" cell_dof_index="0" />
    <dof index="367" value="-2.7642088586993492e-06" cell_index="345" cell_dof_index="3" />
    <dof index="368" value="-1.2868960160177652e-07" cell_index="29" cell_dof_index="2" />
    <dof index="369" value="-3.1499528448765084e-06" cell_index="29" cell_dof_index="5" />
    <dof index="370" value="-7.22056658045353e-08" cell_index="29" cell_dof_index="1" />
    <dof index="371" value="-3.1638494990296603e-06" cell_index="29" cell_dof_index="4" />
    <dof index="372" value="-3.6286772483026136e-08" cell_index="31" cell_dof_index="0" />
    <dof index="373" value="-3.0814875317945121e-06" cell_index="31" cell_dof_index="3" />
    <dof index="374" value="-3.3690832083111859e-08" cell_index="31" cell_dof_index="1" />
    <dof index="375" value="-3.0530774047007523e-06" cell_index="31" cell_dof_index="4" />
    <dof index="376" value="2.3530046729045074e-09" cell_index="54" cell_dof_index="2" />
    <dof index="377" value="-3.0193104001555733e-06" cell_index="54" cell_dof_index="5" />
    <dof index="378" value="-1.8700176225039106e-08" cell_index="138" cell_dof_index="1" />
    <dof index="379" value="-2.9494926560292361e-06" cell_index="138" cell_dof_index="4" />
    <dof index="380" value="1.2286162567927341e-10" cell_index="138" cell_dof_index="2" />
    <dof index="381" value="-2.901258552088064e-06" cell_index="138" cell_dof_index="5" />
    <dof index="382" value="-2.2640398467491871e-09" cell_index="246" cell_dof_index="2" />
    <dof index="383" value="-2.8740411558345221e-06" cell_index="246" cell_dof_index="5" />
    <dof index="384" value="-2.3148365442404803e-08" cell_index="195" cell_dof_index="2" />
    <dof index="385" value="-2.8418372291238344e-06" cell_index="195" cell_dof_index="5" />
    <dof index="386" value="9.4855774716703137e-09" cell_index="483" cell_dof_index="0" />
    <dof index="387" value="-2.8386142400823869e-06" cell_index="483" cell_dof_index="3" />
    <dof index="388" value="-6.0658812500823285e-08" cell_index="203" cell_dof_index="2" />
    <dof index="389" value="-2.8149889788391693e-06" cell_index="203" cell_dof_index="5" />
    <dof index="390" value="2.0481742766736797e-09" cell_index="203" cell_dof_index="0" />
    <dof index="391" value="-2.8114204125611054e-06" cell_index="203" cell_dof_index="3" />
    <dof index="392" value="-1.4225739129539421e-07" cell_index="584" cell_dof_index="1" />
    <dof index="393" value="-3.2178838168844065e-06" cell_index="584" cell_dof_index="4" />
    <dof index="394" value="-1.0981473625188639e-07" cell_index="29" cell_dof_index="0" />
    <dof index="395" value="-3.2775494984550805e-06" cell_index="29" cell_dof_index="3" />
    <dof index="396" value="2.4449821655512497e-09" cell_index="43" cell_dof_index="0" />
    <dof index="397" value="-3.3153576055356038e-06" cell_index="43" cell_dof_index="3" />
    <dof index="398" value="4.5726729548970281e-09" cell_index="317" cell_dof_index="2" />
    <dof index="399" value="-3.1513097411188754e-06" cell_index="317" cell_dof_index="5" />
    <dof index="400" value="4.1347220953836698e-08" cell_index="31" cell_dof_index="2" />
    <dof index="401" value="-3.0809573313504562e-06" cell_index="31" cell_dof_index="5" />
    <dof index="402" value="3.8272589199149436e-08" cell_index="40" cell_dof_index="2" />
    <dof index="403" value="-3.052372208545788e-06" cell_index="40" cell_dof_index="5" />
    <dof index="404" value="6.289571669263934e-08" cell_index="85" cell_dof_index="2" />
    <dof index="405" value="-2.9980868463590963e-06" cell_index="85" cell_dof_index="5" />
    <dof index="406" value="2.0150192397872545e-08" cell_index="155" cell_dof_index="2" />
    <dof index="407" value="-2.9418980281343295e-06" cell_index="155" cell_dof_index="5" />
    <dof index="408" value="2.1141574214843913e-08" cell_index="178" cell_dof_index="0" />
    <dof index="409" value="-2.8903264115515246e-06" cell_index="178" cell_dof_index="3" />
    <dof index="410" value="1.0137177866373927e-09" cell_index="177" cell_dof_index="2" />
    <dof index="411" value="-2.8397413508725887e-06" cell_index="177" cell_dof_index="5" />
    <dof index="412" value="-2.8255809054010524e-08" cell_index="177" cell_dof_index="1" />
    <dof index="413" value="-2.8287087445318267e-06" cell_index="177" cell_dof_index="4" />
    <dof index="414" value="-8.5733353870253853e-08" cell_index="195" cell_dof_index="0" />
    <dof index="415" value="-2.7956781811403289e-06" cell_index="195" cell_dof_index="3" />
    <dof index="416" value="-1.8483169621567e-07" cell_index="235" cell_dof_index="2" />
    <dof index="417" value="-2.720030907761568e-06" cell_index="235" cell_dof_index="5" />
    <dof index="418" value="-1.6836074688326411e-07" cell_index="203" cell_dof_index="1" />
    <dof index="419" value="-2.7654962543868389e-06" cell_index="203" cell_dof_index="4" />
    <dof index="420" value="8.2413229817241245e-08" cell_index="97" cell_dof_index="1" />
    <dof index="421" value="-3.1646552690050701e-06" cell_index="97" cell_dof_index="4" />
    <dof index="422" value="1.1206031089526209e-07" cell_index="96" cell_dof_index="2" />
    <dof index="423" value="-3.2770808090198253e-06" cell_index="96" cell_dof_index="5" />
    <dof index="424" value="1.1849112361834385e-07" cell_index="38" cell_dof_index="0" />
    <dof index="425" value="-3.0395778712184345e-06" cell_index="38" cell_dof_index="3" />
    <dof index="426" value="1.1118007356862445e-07" cell_index="38" cell_dof_index="1" />
    <dof index="427" value="-3.0110581230981314e-06" cell_index="38" cell_dof_index="4" />
    <dof index="428" value="1.2662481825898698e-07" cell_index="85" cell_dof_index="1" />
    <dof index="429" value="-2.9345721056567162e-06" cell_index="85" cell_dof_index="4" />
    <dof index="430" value="6.8852934975758079e-08" cell_index="155" cell_dof_index="1" />
    <dof index="431" value="-2.8995546642953549e-06" cell_index="155" cell_dof_index="4" />
    <dof index="432" value="8.8263254292221651e-08" cell_index="180" cell_dof_index="1" />
    <dof index="433" value="-2.7567222459718775e-06" cell_index="180" cell_dof_index="4" />
    <dof index="434" value="1.899570396347692e-08" cell_index="226" cell_dof_index="1" />
    <dof index="435" value="-2.7655672866012578e-06" cell_index="226" cell_dof_index="4" />
    <dof index="436" value="-5.0151938549688693e-08" cell_index="44" cell_dof_index="0" />
    <dof index="437" value="-2.6938739519545742e-06" cell_index="44" cell_dof_index="3" />
    <dof index="438" value="-1.493938135085539e-07" cell_index="44" cell_dof_index="1" />
    <dof index="439" value="-2.6699751062166524e-06" cell_index="44" cell_dof_index="4" />
    <dof index="440" value="-7.5970351225498991e-08" cell_index="44" cell_dof_index="2" />
    <dof index="441" value="-2.7527018543184061e-06" cell_index="44" cell_dof_index="5" />
    <dof index="442" value="-3.2474200021363636e-07" cell_index="234" cell_dof_index="0" />
    <dof index="443" value="-2.6415301153975982e-06" cell_index="234" cell_dof_index="3" />
    <dof index="444" value="-2.8931715269101191e-07" cell_index="234" cell_dof_index="2" />
    <dof index="445" value="-2.5594011953070149e-06" cell_index="234" cell_dof_index="5" />
    <dof index="446" value="1.6720936904258841e-07" cell_index="97" cell_dof_index="2" />
    <dof index="447" value="-3.0713620114771517e-06" cell_index="97" cell_dof_index="5" />
    <dof index="448" value="1.8057346592237269e-07" cell_index="96" cell_dof_index="1" />
    <dof index="449" value="-3.0826466645690823e-06" cell_index="96" cell_dof_index="4" />
    <dof index="450" value="1.4553907174967629e-07" cell_index="96" cell_dof_index="0" />
    <dof index="451" value="-3.2175940839309309e-06" cell_index="96" cell_dof_index="3" />
    <dof index="452" value="2.0443765538275022e-07" cell_index="38" cell_dof_index="2" />
    <dof index="453" value="-2.9610396255873777e-06" cell_index="38" cell_dof_index="5" />
    <dof index="454" value="1.8732811142659914e-07" cell_index="46" cell_dof_index="2" />
    <dof index="455" value="-2.9315983926898763e-06" cell_index="46" cell_dof_index="5" />
    <dof index="456" value="1.8684929083143055e-07" cell_index="137" cell_dof_index="2" />
    <dof index="457" value="-2.8333247070912259e-06" cell_index="137" cell_dof_index="5" />
    <dof index="458" value="1.5267557775083381e-07" cell_index="218" cell_dof_index="2" />
    <dof index="459" value="-2.5997074292707939e-06" cell_index="218" cell_dof_index="5" />
    <dof index="460" value="6.9678703968411398e-08" cell_index="420" cell_dof_index="2" />
    <dof index="461" value="-2.634532894263872e-06" cell_index="420" cell_dof_index="5" />
    <dof index="462" value="1.0237723702467619e-08" cell_index="167" cell_dof_index="1" />
    <dof index="463" value="-2.5924914123189595e-06" cell_index="167" cell_dof_index="4" />
    <dof index="464" value="-6.6297706537208367e-08" cell_index="280" cell_dof_index="0" />
    <dof index="465" value="-2.4370057940675151e-06" cell_index="280" cell_dof_index="3" />
    <dof index="466" value="-1.194625562467832e-07" cell_index="333" cell_dof_index="1" />
    <dof index="467" value="-2.5648193231679195e-06" cell_index="333" cell_dof_index="4" />
    <dof index="468" value="-2.307086964317339e-07" cell_index="243" cell_dof_index="0" />
    <dof index="469" value="-2.4558229261733934e-06" cell_index="243" cell_dof_index="3" />
    <dof index="470" value="-3.7395919154859182e-07" cell_index="306" cell_dof_index="2" />
    <dof index="471" value="-2.3192768365812075e-06" cell_index="306" cell_dof_index="5" />
    <dof index="472" value="-4.5738268901427589e-07" cell_index="234" cell_dof_index="1" />
    <dof index="473" value="-2.435907186759453e-06" cell_index="234" cell_dof_index="4" />
    <dof index="474" value="2.9570924682658013e-07" cell_index="86" cell_dof_index="1" />
    <dof index="475" value="-2.9434011230847266e-06" cell_index="86" cell_dof_index="4" />
    <dof index="476" value="3.0138576633492024e-07" cell_index="46" cell_dof_index="0" />
    <dof index="477" value="-2.8272011976590435e-06" cell_index="46" cell_dof_index="3" />
    <dof index="478" value="2.7076508316591818e-07" cell_index="46" cell_dof_index="1" />
    <dof index="479" value="-2.7961399038709419e-06" cell_index="46" cell_dof_index="4" />
    <dof index="480" value="2.50271278966289e-07" cell_index="53" cell_dof_index="1" />
    <dof index="481" value="-2.6732923367813985e-06" cell_index="53" cell_dof_index="4" />
    <dof index="482" value="2.3685948861858307e-07" cell_index="217" cell_dof_index="2" />
    <dof index="483" value="-2.3895905357852212e-06" cell_index="217" cell_dof_index="5" />
    <dof index="484" value="9.3089848512452021e-08" cell_index="167" cell_dof_index="0" />
    <dof index="485" value="-2.4657083596688362e-06" cell_index="167" cell_dof_index="3" />
    <dof index="486" value="2.8077570196890648e-08" cell_index="167" cell_dof_index="2" />
    <dof index="487" value="-2.2896405650211285e-06" cell_index="167" cell_dof_index="5" />
    <dof index="488" value="-6.3477626268884231e-08" cell_index="270" cell_dof_index="0" />
    <dof index="489" value="-2.1056620110992375e-06" cell_index="270" cell_dof_index="3" />
    <dof index="490" value="-1.4912601069671106e-07" cell_index="243" cell_dof_index="2" />
    <dof index="491" value="-2.2724534402544194e-06" cell_index="243" cell_dof_index="5" />
    <dof index="492" value="-2.862112293653868e-07" cell_index="171" cell_dof_index="1" />
    <dof index="493" value="-2.1589433359430428e-06" cell_index="171" cell_dof_index="4" />
    <dof index="494" value="-5.506778891434928e-07" cell_index="171" cell_dof_index="0" />
    <dof index="495" value="-2.1742694979065814e-06" cell_index="171" cell_dof_index="3" />
    <dof index="496" value="4.4679333528068975e-07" cell_index="86" cell_dof_index="2" />
    <dof index="497" value="-2.712393410924083e-06" cell_index="86" cell_dof_index="5" />
    <dof index="498" value="3.3696185979718431e-07" cell_index="53" cell_dof_index="2" />
    <dof index="499" value="-2.7061485932588285e-06" cell_index="53" cell_dof_index="5" />
    <dof index="500" value="4.1490671111330477e-07" cell_index="217" cell_dof_index="1" />
    <dof index="501" value="-2.3765779224507482e-06" cell_index="217" cell_dof_index="4" />
    <dof index="502" value="4.004454456463537e-07" cell_index="56" cell_dof_index="0" />
    <dof index="503" value="-2.0855804858438632e-06" cell_index="56" cell_dof_index="3" />
    <dof index="504" value="2.741200205640478e-07" cell_index="250" cell_dof_index="2" />
    <dof index="505" value="-2.0986574955982183e-06" cell_index="250" cell_dof_index="5" />
    <dof index="506" value="1.2269612448098075e-07" cell_index="351" cell_dof_index="1" />
    <dof index="507" value="-2.267492494107253e-06" cell_index="351" cell_dof_index="4" />
    <dof index="508" value="5.9972070087315205e-08" cell_index="181" cell_dof_index="1" />
    <dof index="509" value="-2.0204782331453162e-06" cell_index="181" cell_dof_index="4" />
    <dof index="510" value="6.970741416969463e-08" cell_index="256" cell_dof_index="0" />
    <dof index="511" value="-1.754635078373257e-06" cell_index="256" cell_dof_index="3" />
    <dof index="512" value="-8.9566734628516524e-08" cell_index="271" cell_dof_index="2" />
    <dof index="513" value="-1.7414154456358346e-06" cell_index="271" cell_dof_index="5" />
    <dof index="514" value="-1.829171164222875e-07" cell_index="244" cell_dof_index="2" />
    <dof index="515" value="-2.0018935214052612e-06" cell_index="244" cell_dof_index="5" />
    <dof index="516" value="-4.1016074381596919e-07" cell_index="171" cell_dof_index="2" />
    <dof index="517" value="-1.9739295448641874e-06" cell_index="171" cell_dof_index="5" />
    <dof index="518" value="-6.1355402772165644e-07" cell_index="305" cell_dof_index="1" />
    <dof index="519" value="-1.8555005652318557e-06" cell_index="305" cell_dof_index="4" />
    <dof index="520" value="6.2067692500722412e-07" cell_index="261" cell_dof_index="2" />
    <dof index="521" value="-2.463747061246444e-06" cell_index="261" cell_dof_index="5" />
    <dof index="522" value="7.3915952551189534e-07" cell_index="261" cell_dof_index="0" />
    <dof index="523" value="-2.2236556264417622e-06" cell_index="261" cell_dof_index="3" />
    <dof index="524" value="5.8300414186531685e-07" cell_index="56" cell_dof_index="2" />
    <dof index="525" value="-2.1003012554138019e-06" cell_index="56" cell_dof_index="5" />
    <dof index="526" value="6.0679270737233606e-07" cell_index="56" cell_dof_index="1" />
    <dof index="527" value="-1.8231692216529191e-06" cell_index="56" cell_dof_index="4" />
    <dof index="528" value="4.6023872333719733e-07" cell_index="187" cell_dof_index="2" />
    <dof index="529" value="-1.8064330675726237e-06" cell_index="187" cell_dof_index="5" />
    <dof index="530" value="3.2446773350605012e-07" cell_index="187" cell_dof_index="0" />
    <dof index="531" value="-1.8640896278425276e-06" cell_index="187" cell_dof_index="3" />
    <dof index="532" value="1.7585713111957576e-07" cell_index="181" cell_dof_index="0" />
    <dof index="533" value="-2.0516063684424864e-06" cell_index="181" cell_dof_index="3" />
    <dof index="534" value="2.1394284654330951e-07" cell_index="181" cell_dof_index="2" />
    <dof index="535" value="-1.8179008059349175e-06" cell_index="181" cell_dof_index="5" />
    <dof index="536" value="1.5529469721165937e-07" cell_index="102" cell_dof_index="2" />
    <dof index="537" value="-1.5167828089628913e-06" cell_index="102" cell_dof_index="5" />
    <dof index="538" value="-4.7604570703028324e-08" cell_index="194" cell_dof_index="0" />
    <dof index="539" value="-1.4166305592072204e-06" cell_index="194" cell_dof_index="3" />
    <dof index="540" value="-2.3214598347783912e-07" cell_index="194" cell_dof_index="2" />
    <dof index="541" value="-1.4903088022894052e-06" cell_index="194" cell_dof_index="5" />
    <dof index="542" value="-2.8464547294980264e-07" cell_index="343" cell_dof_index="0" />
    <dof index="543" value="-1.7990493480265485e-06" cell_index="343" cell_dof_index="3" />
    <dof index="544" value="-4.5438222391254818e-07" cell_index="193" cell_dof_index="1" />
    <dof index="545" value="-1.6774872369214803e-06" cell_index="193" cell_dof_index="4" />
    <dof index="546" value="-6.2653184695966161e-07" cell_index="193" cell_dof_index="0" />
    <dof index="547" value="-1.4919985386914631e-06" cell_index="193" cell_dof_index="3" />
    <dof index="548" value="8.318815610711431e-07" cell_index="415" cell_dof_index="2" />
    <dof index="549" value="-1.9848431870441962e-06" cell_index="415" cell_dof_index="5" />
    <dof index="550" value="8.9620143217736414e-07" cell_index="415" cell_dof_index="0" />
    <dof index="551" value="-1.7558787968147148e-06" cell_index="415" cell_dof_index="3" />
    <dof index="552" value="7.674324838245035e-07" cell_index="221" cell_dof_index="2" />
    <dof index="553" value="-1.4297939074694044e-06" cell_index="221" cell_dof_index="5" />
    <dof index="554" value="5.8493933600785715e-07" cell_index="251" cell_dof_index="0" />
    <dof index="555" value="-1.5145012197140172e-06" cell_index="251" cell_dof_index="3" />
    <dof index="556" value="4.1404971117138774e-07" cell_index="187" cell_dof_index="1" />
    <dof index="557" value="-1.6235822375099266e-06" cell_index="187" cell_dof_index="4" />
    <dof index="558" value="2.7950135773913575e-07" cell_index="189" cell_dof_index="0" />
    <dof index="559" value="-1.5885617983633181e-06" cell_index="189" cell_dof_index="3" />
    <dof index="560" value="3.0201594079544561e-07" cell_index="102" cell_dof_index="0" />
    <dof index="561" value="-1.1919410182329977e-06" cell_index="102" cell_dof_index="3" />
    <dof index="562" value="1.2195930466002327e-07" cell_index="102" cell_dof_index="1" />
    <dof index="563" value="-1.2603221959538552e-06" cell_index="102" cell_dof_index="4" />
    <dof index="564" value="-5.7681819199764202e-08" cell_index="190" cell_dof_index="1" />
    <dof index="565" value="-1.0464035719660559e-06" cell_index="190" cell_dof_index="4" />
    <dof index="566" value="-2.7199599090279287e-07" cell_index="194" cell_dof_index="1" />
    <dof index="567" value="-1.1811275510418958e-06" cell_index="194" cell_dof_index="4" />
    <dof index="568" value="-4.0126363801048526e-07" cell_index="193" cell_dof_index="2" />
    <dof index="569" value="-1.4303510358923291e-06" cell_index="193" cell_dof_index="5" />
    <dof index="570" value="-5.6668632345132325e-07" cell_index="341" cell_dof_index="2" />
    <dof index="571" value="-1.0841088554189173e-06" cell_index="341" cell_dof_index="5" />
    <dof index="572" value="9.4233390992961986e-07" cell_index="221" cell_dof_index="1" />
    <dof index="573" value="-1.5234900695130732e-06" cell_index="221" cell_dof_index="4" />
    <dof index="574" value="9.6623179576884269e-07" cell_index="221" cell_dof_index="0" />
    <dof index="575" value="-1.3010572362560356e-06" cell_index="221" cell_dof_index="3" />
    <dof index="576" value="7.1218847580291169e-07" cell_index="321" cell_dof_index="1" />
    <dof index="577" value="-1.2210843494056645e-06" cell_index="321" cell_dof_index="4" />
    <dof index="578" value="4.2754289953512938e-07" cell_index="220" cell_dof_index="2" />
    <dof index="579" value="-1.373507978006686e-06" cell_index="220" cell_dof_index="5" />
    <dof index="580" value="5.3093163163510524e-07" cell_index="220" cell_dof_index="0" />
    <dof index="581" value="-1.0660463325742354e-06" cell_index="220" cell_dof_index="3" />
    <dof index="582" value="3.635808802084268e-07" cell_index="115" cell_dof_index="2" />
    <dof index="583" value="-8.7070689489895321e-07" cell_index="115" cell_dof_index="5" />
    <dof index="584" value="1.5398969698280995e-07" cell_index="115" cell_dof_index="0" />
    <dof index="585" value="-9.2576366884914324e-07" cell_index="115" cell_dof_index="3" />
    <dof index="586" value="2.4994459131763819e-08" cell_index="170" cell_dof_index="2" />
    <dof index="587" value="-8.245851729754747e-07" cell_index="170" cell_dof_index="5" />
    <dof index="588" value="-1.3109263322466536e-07" cell_index="55" cell_dof_index="1" />
    <dof index="589" value="-7.0949897528183542e-07" cell_index="55" cell_dof_index="4" />
    <dof index="590" value="-2.5269858745191277e-07" cell_index="55" cell_dof_index="2" />
    <dof index="591" value="-6.5422745131472353e-07" cell_index="55" cell_dof_index="5" />
    <dof index="592" value="-4.1426753741736974e-07" cell_index="51" cell_dof_index="2" />
    <dof index="593" value="-6.3480338453244273e-07" cell_index="51" cell_dof_index="5" />
    <dof index="594" value="-1.7552165600759579e-07" cell_index="190" cell_dof_index="2" />
    <dof index="595" value="-9.5046211987857895e-07" cell_index="190" cell_dof_index="5" />
    <dof index="596" value="9.7577395274079596e-07" cell_index="406" cell_dof_index="2" />
    <dof index="597" value="-1.08999831825729e-06" cell_index="406" cell_dof_index="5" />
    <dof index="598" value="7.0974805624972046e-07" cell_index="324" cell_dof_index="1" />
    <dof index="599" value="-8.623190795261549e-07" cell_index="324" cell_dof_index="4" />
    <dof index="600" value="5.0462846587193882e-07" cell_index="323" cell_dof_index="2" />
    <dof index="601" value="-7.348531767395788e-07" cell_index="323" cell_dof_index="5" />
    <dof index="602" value="3.6971102400601759e-07" cell_index="173" cell_dof_index="0" />
    <dof index="603" value="-5.8615676513626957e-07" cell_index="173" cell_dof_index="3" />
    <dof index="604" value="2.2253325256744414e-07" cell_index="219" cell_dof_index="2" />
    <dof index="605" value="-6.8604421166857607e-07" cell_index="219" cell_dof_index="5" />
    <dof index="606" value="6.3315254868049386e-08" cell_index="219" cell_dof_index="1" />
    <dof index="607" value="-6.0721717962941593e-07" cell_index="219" cell_dof_index="4" />
    <dof index="608" value="-1.139798337991235e-07" cell_index="142" cell_dof_index="2" />
    <dof index="609" value="-4.9853194337171936e-07" cell_index="142" cell_dof_index="5" />
    <dof index="610" value="-2.0318175348225681e-07" cell_index="45" cell_dof_index="2" />
    <dof index="611" value="-5.4172564589155893e-07" cell_index="45" cell_dof_index="5" />
    <dof index="612" value="-2.5307300206438759e-07" cell_index="45" cell_dof_index="1" />
    <dof index="613" value="-4.9513130397329748e-07" cell_index="45" cell_dof_index="4" />
    <dof index="614" value="-2.9373103454023292e-07" cell_index="51" cell_dof_index="1" />
    <dof index="615" value="-3.2562312609186796e-07" cell_index="51" cell_dof_index="4" />
    <dof index="616" value="9.7474061346674608e-07" cell_index="406" cell_dof_index="0" />
    <dof index="617" value="-8.9109402892385457e-07" cell_index="406" cell_dof_index="3" />
    <dof index="618" value="7.8811367479692075e-07" cell_index="182" cell_dof_index="2" />
    <dof index="619" value="-6.9517168010974943e-07" cell_index="182" cell_dof_index="5" />
    <dof index="620" value="6.4726668080387521e-07" cell_index="228" cell_dof_index="0" />
    <dof index="621" value="-6.0193505363249814e-07" cell_index="228" cell_dof_index="3" />
    <dof index="622" value="4.5825664207815379e-07" cell_index="173" cell_dof_index="1" />
    <dof index="623" value="-4.2926185843648273e-07" cell_index="173" cell_dof_index="4" />
    <dof index="624" value="2.497795375226284e-07" cell_index="101" cell_dof_index="1" />
    <dof index="625" value="-4.6137371692077398e-07" cell_index="101" cell_dof_index="4" />
    <dof index="626" value="1.5259590479680564e-07" cell_index="101" cell_dof_index="2" />
    <dof index="627" value="-5.2927501106133953e-07" cell_index="101" cell_dof_index="5" />
    <dof index="628" value="1.2766598523607864e-08" cell_index="222" cell_dof_index="2" />
    <dof index="629" value="-4.1050876680093462e-07" cell_index="222" cell_dof_index="5" />
    <dof index="630" value="-9.9237243043872533e-08" cell_index="87" cell_dof_index="2" />
    <dof index="631" value="-3.41485816069664e-07" cell_index="87" cell_dof_index="5" />
    <dof index="632" value="-1.7271133412914027e-07" cell_index="45" cell_dof_index="0" />
    <dof index="633" value="-3.5916406773158297e-07" cell_index="45" cell_dof_index="3" />
    <dof index="634" value="-2.0984508652402072e-07" cell_index="47" cell_dof_index="1" />
    <dof index="635" value="-3.1974111047058412e-07" cell_index="47" cell_dof_index="4" />
    <dof index="636" value="-2.0368909593178912e-07" cell_index="19" cell_dof_index="2" />
    <dof index="637" value="-1.9431996870844163e-07" cell_index="19" cell_dof_index="5" />
    <dof index="638" value="-1.5809317928802458e-07" cell_index="60" cell_dof_index="0" />
    <dof index="639" value="-1.5378485314972508e-07" cell_index="60" cell_dof_index="3" />
    <dof index="640" value="9.6254210633959748e-07" cell_index="249" cell_dof_index="1" />
    <dof index="641" value="-7.0779495087979483e-07" cell_index="249" cell_dof_index="4" />
    <dof index="642" value="9.4412633000139962e-07" cell_index="182" cell_dof_index="0" />
    <dof index="643" value="-5.3805790918065601e-07" cell_index="182" cell_dof_index="3" />
    <dof index="644" value="7.5086308394386533e-07" cell_index="182" cell_dof_index="1" />
    <dof index="645" value="-4.1323878339462057e-07" cell_index="182" cell_dof_index="4" />
    <dof index="646" value="5.699849040987376e-07" cell_index="293" cell_dof_index="0" />
    <dof index="647" value="-3.0772578750954303e-07" cell_index="293" cell_dof_index="3" />
    <dof index="648" value="4.1611019384865078e-07" cell_index="293" cell_dof_index="1" />
    <dof index="649" value="-2.0788122839021938e-07" cell_index="293" cell_dof_index="4" />
    <dof index="650" value="3.1498176940995727e-07" cell_index="262" cell_dof_index="0" />
    <dof index="651" value="-3.3249776885670172e-07" cell_index="262" cell_dof_index="3" />
    <dof index="652" value="1.8230331933076616e-07" cell_index="237" cell_dof_index="1" />
    <dof index="653" value="-2.5651816366280146e-07" cell_index="237" cell_dof_index="4" />
    <dof index="654" value="1.2495340196575541e-07" cell_index="101" cell_dof_index="0" />
    <dof index="655" value="-3.754348149514636e-07" cell_index="101" cell_dof_index="3" />
    <dof index="656" value="9.2448243612589262e-09" cell_index="327" cell_dof_index="2" />
    <dof index="657" value="-2.7074195733592533e-07" cell_index="327" cell_dof_index="5" />
    <dof index="658" value="-8.322920857715001e-08" cell_index="58" cell_dof_index="2" />
    <dof index="659" value="-2.289691046485537e-07" cell_index="58" cell_dof_index="5" />
    <dof index="660" value="-1.4607361999708741e-07" cell_index="58" cell_dof_index="1" />
    <dof index="661" value="-2.3762497778376584e-07" cell_index="58" cell_dof_index="4" />
    <dof index="662" value="-1.7339039842859143e-07" cell_index="59" cell_dof_index="2" />
    <dof index="663" value="-2.0685306758106697e-07" cell_index="59" cell_dof_index="5" />
    <dof index="664" value="-1.3866545498676703e-07" cell_index="19" cell_dof_index="0" />
    <dof index="665" value="-9.7095953257958854e-08" cell_index="19" cell_dof_index="3" />
    <dof index="666" value="-1.2246989001851649e-07" cell_index="19" cell_dof_index="1" />
    <dof index="667" value="-1.0157165470891102e-07" cell_index="19" cell_dof_index="4" />
    <dof index="668" value="0" cell_index="588" cell_dof_index="0" />
    <dof index="669" value="0" cell_index="588" cell_dof_index="3" />
    <dof index="670" value="5.9856494573734311e-07" cell_index="228" cell_dof_index="2" />
    <dof index="671" value="-4.4865433560867691e-07" cell_index="228" cell_dof_index="5" />
    <dof index="672" value="9.2370392123674431e-07" cell_index="398" cell_dof_index="2" />
    <dof index="673" value="-3.8327345831089388e-07" cell_index="398" cell_dof_index="5" />
    <dof index="674" value="7.5003069939671857e-07" cell_index="386" cell_dof_index="2" />
    <dof index="675" value="-2.5639091350513414e-07" cell_index="386" cell_dof_index="5" />
    <dof index="676" value="5.9391950819180434e-07" cell_index="389" cell_dof_index="2" />
    <dof index="677" value="-1.4978894106984222e-07" cell_index="389" cell_dof_index="5" />
    <dof index="678" value="4.0505495943190346e-07" cell_index="163" cell_dof_index="2" />
    <dof index="679" value="-2.2826389297267341e-08" cell_index="163" cell_dof_index="5" />
    <dof index="680" value="2.6370437099879386e-07" cell_index="163" cell_dof_index="0" />
    <dof index="681" value="-1.2696432054332539e-07" cell_index="163" cell_dof_index="3" />
    <dof index="682" value="1.5342256411882532e-07" cell_index="198" cell_dof_index="2" />
    <dof index="683" value="-1.4500224108075119e-07" cell_index="198" cell_dof_index="5" />
    <dof index="684" value="6.2532891720333385e-08" cell_index="143" cell_dof_index="2" />
    <dof index="685" value="-1.8314943281844543e-07" cell_index="143" cell_dof_index="5" />
    <dof index="686" value="-7.0144065170346935e-08" cell_index="117" cell_dof_index="1" />
    <dof index="687" value="-1.4209240462250422e-07" cell_index="117" cell_dof_index="4" />
    <dof index="688" value="-1.2287414526615571e-07" cell_index="58" cell_dof_index="0" />
    <dof index="689" value="-1.5558405745198183e-07" cell_index="58" cell_dof_index="3" />
    <dof index="690" value="-1.41955673259326e-07" cell_index="59" cell_dof_index="1" />
    <dof index="691" value="-1.3733579488992527e-07" cell_index="59" cell_dof_index="4" />
    <dof index="692" value="-1.2695845129777222e-07" cell_index="355" cell_dof_index="2" />
    <dof index="693" value="-7.4340009440336823e-08" cell_index="355" cell_dof_index="5" />
    <dof index="694" value="0" cell_index="123" cell_dof_index="0" />
    <dof index="695" value="0" cell_index="123" cell_dof_index="3" />
    <dof index="696" value="0" cell_index="52" cell_dof_index="0" />
    <dof index="697" value="0" cell_index="52" cell_dof_index="3" />
    <dof index="698" value="9.0529548537874313e-07" cell_index="386" cell_dof_index="0" />
    <dof index="699" value="-2.440368689242989e-07" cell_index="386" cell_dof_index="3" />
    <dof index="700" value="7.5641274400457423e-07" cell_index="386" cell_dof_index="1" />
    <dof index="701" value="-1.1151346102286856e-07" cell_index="386" cell_dof_index="4" />
    <dof index="702" value="6.035003884931671e-07" cell_index="287" cell_dof_index="0" />
    <dof index="703" value="1.543100403820914e-10" cell_index="287" cell_dof_index="3" />
    <dof index="704" value="4.8280477501421355e-07" cell_index="257" cell_dof_index="1" />
    <dof index="705" value="1.2781029873123777e-07" cell_index="257" cell_dof_index="4" />
    <dof index="706" value="3.66817439342967e-07" cell_index="257" cell_dof_index="2" />
    <dof index="707" value="7.921125513507087e-08" cell_index="257" cell_dof_index="5" />
    <dof index="708" value="2.4640691883511947e-07" cell_index="163" cell_dof_index="1" />
    <dof index="709" value="5.3276872910635189e-08" cell_index="163" cell_dof_index="4" />
    <dof index="710" value="8.3562674896651556e-08" cell_index="121" cell_dof_index="2" />
    <dof index="711" value="-4.3568330283360489e-08" cell_index="121" cell_dof_index="5" />
    <dof index="712" value="-5.9968985181734437e-08" cell_index="72" cell_dof_index="2" />
    <dof index="713" value="-6.9161225015961491e-08" cell_index="72" cell_dof_index="5" />
    <dof index="714" value="-1.0392825013954703e-07" cell_index="69" cell_dof_index="2" />
    <dof index="715" value="-8.8308380850593359e-08" cell_index="69" cell_dof_index="5" />
    <dof index="716" value="-1.1956419628726667e-07" cell_index="67" cell_dof_index="2" />
    <dof index="717" value="-7.7581898470247361e-08" cell_index="67" cell_dof_index="5" />
    <dof index="718" value="-9.4850373066199763e-08" cell_index="68" cell_dof_index="0" />
    <dof index="719" value="-3.5748361225767807e-08" cell_index="68" cell_dof_index="3" />
    <dof index="720" value="0" cell_index="74" cell_dof_index="0" />
    <dof index="721" value="0" cell_index="74" cell_dof_index="3" />
    <dof index="722" value="8.9110695992214431e-07" cell_index="616" cell_dof_index="2" />
    <dof index="723" value="-1.1435881825681295e-07" cell_index="616" cell_dof_index="5" />
    <dof index="724" value="8.8209616871439401e-07" cell_index="184" cell_dof_index="0" />
    <dof index="725" value="1.1520096380600015e-08" cell_index="184" cell_dof_index="3" />
    <dof index="726" value="7.3994196826566838e-07" cell_index="184" cell_dof_index="2" />
    <dof index="727" value="7.3663139697402093e-08" cell_index="184" cell_dof_index="5" />
    <dof index="728" value="6.1668995420874581e-07" cell_index="258" cell_dof_index="2" />
    <dof index="729" value="1.2056766702291108e-07" cell_index="258" cell_dof_index="5" />
    <dof index="730" value="6.1537964383001068e-07" cell_index="613" cell_dof_index="0" />
    <dof index="731" value="2.6056087106156435e-07" cell_index="613" cell_dof_index="3" />
    <dof index="732" value="4.8322404564499374e-07" cell_index="612" cell_dof_index="2" />
    <dof index="733" value="2.5102124619373962e-07" cell_index="612" cell_dof_index="5" />
    <dof index="734" value="3.5292148847914596e-07" cell_index="288" cell_dof_index="0" />
    <dof index="735" value="2.3458806142942394e-07" cell_index="288" cell_dof_index="3" />
    <dof index="736" value="2.3437191289834861e-07" cell_index="625" cell_dof_index="2" />
    <dof index="737" value="2.1381573267360342e-07" cell_index="625" cell_dof_index="5" />
    <dof index="738" value="1.7392597468176703e-07" cell_index="172" cell_dof_index="2" />
    <dof index="739" value="1.1574591231027426e-07" cell_index="172" cell_dof_index="5" />
    <dof index="740" value="5.8271576541219865e-08" cell_index="140" cell_dof_index="2" />
    <dof index="741" value="6.4366611362653439e-08" cell_index="140" cell_dof_index="5" />
    <dof index="742" value="-4.9599229290704913e-08" cell_index="64" cell_dof_index="2" />
    <dof index="743" value="-6.1223168353147402e-09" cell_index="64" cell_dof_index="5" />
    <dof index="744" value="-8.9446344542683391e-08" cell_index="64" cell_dof_index="0" />
    <dof index="745" value="-3.534918559113328e-08" cell_index="64" cell_dof_index="3" />
    <dof index="746" value="-1.0321162077808758e-07" cell_index="67" cell_dof_index="1" />
    <dof index="747" value="-3.435325549029198e-08" cell_index="67" cell_dof_index="4" />
    <dof index="748" value="-9.4291707069210577e-08" cell_index="68" cell_dof_index="2" />
    <dof index="749" value="-6.0248006378834215e-09" cell_index="68" cell_dof_index="5" />
    <dof index="750" value="-6.3754192050515958e-08" cell_index="68" cell_dof_index="1" />
    <dof index="751" value="-1.0750031452592298e-08" cell_index="68" cell_dof_index="4" />
    <dof index="752" value="0" cell_index="592" cell_dof_index="1" />
    <dof index="753" value="0" cell_index="592" cell_dof_index="4" />
    <dof index="754" value="8.7872297080416413e-07" cell_index="184" cell_dof_index="1" />
    <dof index="755" value="1.3731971116573571e-07" cell_index="184" cell_dof_index="4" />
    <dof index="756" value="7.4823433259884839e-07" cell_index="258" cell_dof_index="1" />
    <dof index="757" value="2.6395262102719347e-07" cell_index="258" cell_dof_index="4" />
    <dof index="758" value="1.2564129602196073e-07" cell_index="172" cell_dof_index="0" />
    <dof index="759" value="1.8219874189777185e-07" cell_index="172" cell_dof_index="3" />
    <dof index="760" value="3.6880894409130887e-08" cell_index="443" cell_dof_index="2" />
    <dof index="761" value="1.487734823924381e-07" cell_index="443" cell_dof_index="5" />
    <dof index="762" value="-3.947966473511807e-08" cell_index="118" cell_dof_index="2" />
    <dof index="763" value="5.2910925627234292e-08" cell_index="118" cell_dof_index="5" />
    <dof index="764" value="-7.7295357361474529e-08" cell_index="64" cell_dof_index="1" />
    <dof index="765" value="1.3729042383069087e-08" cell_index="64" cell_dof_index="4" />
    <dof index="766" value="-9.0092709502812973e-08" cell_index="75" cell_dof_index="2" />
    <dof index="767" value="7.2283431399327285e-09" cell_index="75" cell_dof_index="5" />
    <dof index="768" value="-9.4191168118787451e-08" cell_index="76" cell_dof_index="2" />
    <dof index="769" value="1.4528114546136857e-08" cell_index="76" cell_dof_index="5" />
    <dof index="770" value="-6.7462515696035085e-08" cell_index="90" cell_dof_index="0" />
    <dof index="771" value="-1.0007366278158518e-08" cell_index="90" cell_dof_index="3" />
    <dof index="772" value="8.7792914438042859e-07" cell_index="623" cell_dof_index="0" />
    <dof index="773" value="2.6474644745092891e-07" cell_index="623" cell_dof_index="3" />
    <dof index="774" value="-3.0409428245743331e-08" cell_index="88" cell_dof_index="1" />
    <dof index="775" value="1.1225051364218298e-07" cell_index="88" cell_dof_index="4" />
    <dof index="776" value="-6.8500025732193725e-08" cell_index="75" cell_dof_index="0" />
    <dof index="777" value="5.9782561550241611e-08" cell_index="75" cell_dof_index="3" />
    <dof index="778" value="-8.0640394184545728e-08" cell_index="75" cell_dof_index="1" />
    <dof index="779" value="4.7136620636013791e-08" cell_index="75" cell_dof_index="4" />
    <dof index="780" value="-9.2185850529702497e-08" cell_index="80" cell_dof_index="1" />
    <dof index="781" value="5.1386172828242226e-08" cell_index="80" cell_dof_index="4" />
    <dof index="782" value="-7.3275843713100177e-08" cell_index="80" cell_dof_index="2" />
    <dof index="783" value="7.1890104865978861e-08" cell_index="80" cell_dof_index="5" />
  </function_data>
</dolfin>
